README.txt
setup.py
Products/__init__.py
Products.DisableSelectDefaultView.egg-info/PKG-INFO
Products.DisableSelectDefaultView.egg-info/SOURCES.txt
Products.DisableSelectDefaultView.egg-info/dependency_links.txt
Products.DisableSelectDefaultView.egg-info/entry_points.txt
Products.DisableSelectDefaultView.egg-info/namespace_packages.txt
Products.DisableSelectDefaultView.egg-info/not-zip-safe
Products.DisableSelectDefaultView.egg-info/requires.txt
Products.DisableSelectDefaultView.egg-info/top_level.txt
Products/DisableSelectDefaultView/__init__.py