Metadata-Version: 1.0
Name: Products.DisableSelectDefaultView
Version: 1.0
Summary: Simple product that disables setting of default view for everyone.
Home-page: http://www.nidelven-it.no/d
Author: Morten W. Petersen
Author-email: info@nidelven-it.no
License: GPL
Keywords: python plone display layout
Platform: UNKNOWN
Classifier: Programming Language :: Python
Classifier: Framework :: Plone
Classifier: Intended Audience :: Developers
Classifier: Operating System :: OS Independent
